{"updated":1784305913936,"count":25,"players":[{"pos":1,"name":"Kenichi_","rank":"prisma","playtimeMs":5294337204,"sessions":544,"lastSeen":1784305734503},{"pos":2,"name":"Ladymia","rank":"ascend","playtimeMs":4375302580,"sessions":333,"lastSeen":1784305828072},{"pos":3,"name":"Valkyr","rank":"ascendmas","playtimeMs":4256919105,"sessions":1119,"lastSeen":1784305458861},{"pos":4,"name":"Acidmind","rank":"default","playtimeMs":4167733350,"sessions":380,"lastSeen":1784305888612},{"pos":5,"name":"Tarhz","rank":"prisma","playtimeMs":4035970973,"sessions":910,"lastSeen":1784305628317},{"pos":6,"name":"Reminis","rank":"prisma","playtimeMs":3391568347,"sessions":468,"lastSeen":1784305777107},{"pos":7,"name":"UIGO888","rank":"prisma","playtimeMs":2829717053,"sessions":19,"lastSeen":1784125991419},{"pos":8,"name":"Elian","rank":"prisma","playtimeMs":2822583692,"sessions":519,"lastSeen":1784305834833},{"pos":9,"name":"Anavi","rank":"prisma","playtimeMs":2672713700,"sessions":228,"lastSeen":1784168912043},{"pos":10,"name":"Alatus_Uchiha_s","rank":"default","playtimeMs":2544016762,"sessions":44,"lastSeen":1784207874502},{"pos":11,"name":"xJEDELx","rank":"prisma","playtimeMs":2508649930,"sessions":3,"lastSeen":1783885343574},{"pos":12,"name":"Dkazuto938","rank":"ascend","playtimeMs":2435784141,"sessions":373,"lastSeen":1784265645253},{"pos":13,"name":"Jhapo","rank":"default","playtimeMs":2432334277,"sessions":3,"lastSeen":1783876588810},{"pos":14,"name":"Alejangustha","rank":"default","playtimeMs":2415834815,"sessions":32,"lastSeen":1784039995245},{"pos":15,"name":"Drakarhys","rank":"default","playtimeMs":2307591221,"sessions":335,"lastSeen":1784271499081},{"pos":16,"name":"Dag","rank":"pulse","playtimeMs":2204676759,"sessions":386,"lastSeen":1784305719566},{"pos":17,"name":"SoyMikashi","rank":"core","playtimeMs":2114803497,"sessions":76,"lastSeen":1784235775919},{"pos":18,"name":"Senya_g_m","rank":"prisma","playtimeMs":2047395835,"sessions":3,"lastSeen":1783944004933},{"pos":19,"name":"STARNIIC","rank":"ascend","playtimeMs":2027979243,"sessions":620,"lastSeen":1784289557469},{"pos":20,"name":"Diospala","rank":"","playtimeMs":1912817696,"sessions":2,"lastSeen":1782851698255},{"pos":21,"name":"PandaSempai","rank":"prisma","playtimeMs":1871069840,"sessions":602,"lastSeen":1784035631252},{"pos":22,"name":"XxZankaxX","rank":"default","playtimeMs":1680451910,"sessions":46,"lastSeen":1784299851076},{"pos":23,"name":"Ronin457","rank":"default","playtimeMs":1572336246,"sessions":39,"lastSeen":1784134137403},{"pos":24,"name":"Cinque","rank":"default","playtimeMs":1556050899,"sessions":13,"lastSeen":1783114885321},{"pos":25,"name":"Hansser","rank":"default","playtimeMs":1527081515,"sessions":2,"lastSeen":1783285328785}]}